{"box_data": [{"position": {"minX": 30.418975830078125, "minY": 54.273155212402344, "maxX": 221.14540100097656, "maxY": 132.94354248046875}, "class_id": 4, "box_caption": "saipa_saina 0.674", "scores": {"class_score": 0.6739696860313416}, "domain": "pixel"}, {"position": {"minX": 28.837120056152344, "minY": 53.0955924987793, "maxX": 220.5008544921875, "maxY": 134.2661590576172}, "class_id": 1, "box_caption": "kia_cerato 0.182", "scores": {"class_score": 0.18179604411125183}, "domain": "pixel"}, {"position": {"minX": 30.894973754882812, "minY": 52.806663513183594, "maxX": 222.5331573486328, "maxY": 135.87005615234375}, "class_id": 0, "box_caption": "iranKhodro_dena 0.144", "scores": {"class_score": 0.14413157105445862}, "domain": "pixel"}, {"position": {"minX": 28.837120056152344, "minY": 53.0955924987793, "maxX": 220.5008544921875, "maxY": 134.2661590576172}, "class_id": 2, "box_caption": "mazda_3 0.138", "scores": {"class_score": 0.13810370862483978}, "domain": "pixel"}, {"position": {"minX": 29.05455780029297, "minY": 55.508056640625, "maxX": 221.68692016601562, "maxY": 134.01324462890625}, "class_id": 3, "box_caption": "peugeot_206 0.063", "scores": {"class_score": 0.06282646209001541}, "domain": "pixel"}, {"position": {"minX": 86.11167907714844, "minY": 53.72265625, "maxX": 165.43235778808594, "maxY": 129.72494506835938}, "class_id": 4, "box_caption": "saipa_saina 0.008", "scores": {"class_score": 0.007561856880784035}, "domain": "pixel"}, {"position": {"minX": 86.11167907714844, "minY": 53.72265625, "maxX": 165.43235778808594, "maxY": 129.72494506835938}, "class_id": 0, "box_caption": "iranKhodro_dena 0.002", "scores": {"class_score": 0.001989679643884301}, "domain": "pixel"}, {"position": {"minX": 86.11167907714844, "minY": 53.72265625, "maxX": 165.43235778808594, "maxY": 129.72494506835938}, "class_id": 2, "box_caption": "mazda_3 0.002", "scores": {"class_score": 0.001896102912724018}, "domain": "pixel"}, {"position": {"minX": 86.11167907714844, "minY": 53.72265625, "maxX": 165.43235778808594, "maxY": 129.72494506835938}, "class_id": 3, "box_caption": "peugeot_206 0.002", "scores": {"class_score": 0.001866447157226503}, "domain": "pixel"}, {"position": {"minX": 86.11167907714844, "minY": 53.72265625, "maxX": 165.43235778808594, "maxY": 129.72494506835938}, "class_id": 1, "box_caption": "kia_cerato 0.002", "scores": {"class_score": 0.0016403633635491133}, "domain": "pixel"}], "class_labels": {"0": "iranKhodro_dena", "1": "kia_cerato", "2": "mazda_3", "3": "peugeot_206", "4": "saipa_saina"}}